<annotation><folder>images</folder><filename>image20240402132739_jpg.png</filename><size><width>480</width><height>270</height><depth>3</depth></size><object><name>car</name><pose>Unspecified</pose><truncated>0</truncated><occluded>0</occluded><difficult>0</difficult><bndbox><xmin>388</xmin><ymin>165</ymin><xmax>397</xmax><ymax>173</ymax></bndbox></object><object><name>car</name><pose>Unspecified</pose><truncated>0</truncated><occluded>0</occluded><difficult>0</difficult><bndbox><xmin>418</xmin><ymin>161</ymin><xmax>426</xmax><ymax>167</ymax></bndbox></object><object><name>sheep</name><pose>Unspecified</pose><truncated>0</truncated><occluded>0</occluded><difficult>0</difficult><bndbox><xmin>117</xmin><ymin>168</ymin><xmax>140</xmax><ymax>190</ymax></bndbox></object><object><name>sheep</name><pose>Unspecified</pose><truncated>0</truncated><occluded>0</occluded><difficult>0</difficult><bndbox><xmin>0</xmin><ymin>200</ymin><xmax>17</xmax><ymax>269</ymax></bndbox></object><object><name>sheep</name><pose>Unspecified</pose><truncated>0</truncated><occluded>0</occluded><difficult>0</difficult><bndbox><xmin>300</xmin><ymin>190</ymin><xmax>328</xmax><ymax>218</ymax></bndbox></object><object><name>sheep</name><pose>Unspecified</pose><truncated>0</truncated><occluded>0</occluded><difficult>0</difficult><bndbox><xmin>252</xmin><ymin>177</ymin><xmax>262</xmax><ymax>193</ymax></bndbox></object></annotation>